Metadata-Version: 2.1
Name: flash-cosine-sim-attention
Version: 0.1.35
Summary: Flash Cosine Similarity Attention
Home-page: https://github.com/lucidrains/flash-cosine-sim-attention
Author: Phil Wang
Author-email: lucidrains@gmail.com
License: MIT
Keywords: artificial intelligence,deep learning,attention mechanism
Classifier: Development Status :: 4 - Beta
Classifier: Intended Audience :: Developers
Classifier: Topic :: Scientific/Engineering :: Artificial Intelligence
Classifier: License :: OSI Approved :: MIT License
Classifier: Programming Language :: Python :: 3.6
License-File: LICENSE
